neo/Blockchain.py
neo/EventHub.py
neo/Settings.py
neo/UserPreferences.py
neo/__init__.py
neo/logging.py
neo/test_logging.py
neo/test_preferences.py
neo/test_settings.py
neo/Core/AssetType.py
neo/Core/BigInteger.py
neo/Core/Block.py
neo/Core/BlockBase.py
neo/Core/Blockchain.py
neo/Core/CoinReference.py
neo/Core/Fixed8.py
neo/Core/FunctionCode.py
neo/Core/Header.py
neo/Core/Helper.py
neo/Core/KeyPair.py
neo/Core/Mixins.py
neo/Core/Size.py
neo/Core/UInt160.py
neo/Core/UInt256.py
neo/Core/UIntBase.py
neo/Core/Utils.py
neo/Core/VerificationCode.py
neo/Core/Witness.py
neo/Core/__init__.py
neo/Core/test_block.py
neo/Core/test_block_hash.py
neo/Core/test_function_code.py
neo/Core/test_genesis_block.py
neo/Core/Cryptography/Crypto.py
neo/Core/Cryptography/ECCurve.py
neo/Core/Cryptography/Helper.py
neo/Core/Cryptography/MerkleTree.py
neo/Core/Cryptography/__init__.py
neo/Core/IO/BinaryReader.py
neo/Core/IO/BinaryWriter.py
neo/Core/IO/Mixins.py
neo/Core/IO/__init__.py
neo/Core/State/AccountState.py
neo/Core/State/AssetState.py
neo/Core/State/BlockState.py
neo/Core/State/CoinState.py
neo/Core/State/ContractState.py
neo/Core/State/SpentCoinState.py
neo/Core/State/StateBase.py
neo/Core/State/StateDescriptor.py
neo/Core/State/StorageItem.py
neo/Core/State/StorageKey.py
neo/Core/State/TransactionState.py
neo/Core/State/UnspentCoinState.py
neo/Core/State/ValidatorState.py
neo/Core/State/__init__.py
neo/Core/State/test_states.py
neo/Core/TX/ClaimTransaction.py
neo/Core/TX/EnrollmentTransaction.py
neo/Core/TX/InvocationTransaction.py
neo/Core/TX/IssueTransaction.py
neo/Core/TX/MinerTransaction.py
neo/Core/TX/PublishTransaction.py
neo/Core/TX/RegisterTransaction.py
neo/Core/TX/StateTransaction.py
neo/Core/TX/Transaction.py
neo/Core/TX/TransactionAttribute.py
neo/Core/TX/__init__.py
neo/Core/TX/test_transactions.py
neo/Core/bin/__init__.py
neo/Core/bin/cli.py
neo/Core/tests/__init__.py
neo/Core/tests/test_KeyPair.py
neo/Core/tests/test_cli.py
neo/Core/tests/test_cryptography.py
neo_python-0.9.1.dist-info/LICENSE.md
neo_python-0.9.1.dist-info/METADATA
neo_python-0.9.1.dist-info/WHEEL
neo_python-0.9.1.dist-info/entry_points.txt
neo_python-0.9.1.dist-info/top_level.txt
neo_python-0.9.1.dist-info/RECORD
