Metadata-Version: 2.1
Name: neo-python
Version: 0.9.1
Summary: Python Node and SDK for the NEO blockchain
Home-page: https://github.com/CityOfZion/neo-python
Author: Thomas Saunders
Author-email: tom@cityofzion.io
Maintainer: Erik van den Brink
Maintainer-email: erik@cityofzion.io
License: MIT license
Keywords: neo,python,node
Platform: UNKNOWN
Classifier: Development Status :: 3 - Alpha
Classifier: Intended Audience :: Developers
Classifier: License :: OSI Approved :: MIT License
Classifier: Natural Language :: English
Classifier: Programming Language :: Python :: 3
Classifier: Programming Language :: Python :: 3.7
Requires-Python: >=3.7
Requires-Dist: aenum (==2.2.1)
Requires-Dist: aiohttp (==3.6.0)
Requires-Dist: aiohttp-cors (==0.7.0)
Requires-Dist: astor (==0.8.0)
Requires-Dist: asynctest (==0.13.0)
Requires-Dist: async-timeout (==3.0.1)
Requires-Dist: attrs (==19.1.0)
Requires-Dist: autopep8 (==1.4.4)
Requires-Dist: base58 (==1.0.3)
Requires-Dist: bitcoin (==1.1.42)
Requires-Dist: certifi (==2019.6.16)
Requires-Dist: chardet (==3.0.4)
Requires-Dist: coverage (==4.5.4)
Requires-Dist: coveralls (==1.8.2)
Requires-Dist: coz-bytecode (==0.5.1)
Requires-Dist: docopt (==0.6.2)
Requires-Dist: ecdsa (==0.13.2)
Requires-Dist: idna (==2.8)
Requires-Dist: logzero (==1.5.0)
Requires-Dist: mmh3 (==2.5.1)
Requires-Dist: mock (==3.0.5)
Requires-Dist: mpmath (==1.1.0)
Requires-Dist: multidict (==4.5.2)
Requires-Dist: neo-boa (==0.6.0)
Requires-Dist: neo-python-rpc (==0.2.1)
Requires-Dist: pbr (==5.4.3)
Requires-Dist: peewee (==3.10.0)
Requires-Dist: plyvel (==1.1.0)
Requires-Dist: prompt-toolkit (==2.0.9)
Requires-Dist: psutil (==5.6.3)
Requires-Dist: pycodestyle (==2.5.0)
Requires-Dist: pycryptodome (==3.9.0)
Requires-Dist: pymitter (==0.2.3)
Requires-Dist: pyparsing (==2.4.2)
Requires-Dist: pytz (==2019.2)
Requires-Dist: requests (==2.22.0)
Requires-Dist: scrypt (==0.8.13)
Requires-Dist: six (==1.12.0)
Requires-Dist: tqdm (==4.29.1)
Requires-Dist: urllib3 (==1.25.3)
Requires-Dist: wcwidth (==0.1.7)
Requires-Dist: yarl (==1.3.0)
